cmgr/__init__.py
cmgr/__main__.py
cmgr/command_line.py
cmgr-0.2.3.dist-info/LICENSE
cmgr-0.2.3.dist-info/METADATA
cmgr-0.2.3.dist-info/WHEEL
cmgr-0.2.3.dist-info/entry_points.txt
cmgr-0.2.3.dist-info/top_level.txt
cmgr-0.2.3.dist-info/RECORD
