Metadata-Version: 2.1
Name: cmgr
Version: 0.2.3
Summary: A configuratable config manager for your packages.
Author-email: Kyan <k@kyan001.com>
License: BSD 3-Clause License
Project-URL: Homepage, https://github.com/kyan001/PyConfigManager
Project-URL: Changelog, https://github.com/kyan001/PyConfigManager/blob/master/CHANGELOG.md
Project-URL: Issue Tracker, https://github.com/kyan001/PyConfigManager/issues
Project-URL: Source Code, https://github.com/kyan001/PyConfigManager
Keywords: python3,configuratable,config,manager
Classifier: Intended Audience :: Developers
Classifier: Intended Audience :: End Users/Desktop
Classifier: License :: OSI Approved :: BSD License
Classifier: Programming Language :: Python :: 3
Classifier: Programming Language :: Python :: 3 :: Only
Requires-Python: >=3.8
License-File: LICENSE
Requires-Dist: consoleiotools
Requires-Dist: consolecmdtools>=6.6.1
Requires-Dist: click
Provides-Extra: dev
Requires-Dist: build; extra == "dev"
Requires-Dist: twine; extra == "dev"
